cpnetlearn/bayesian_network.py
cpnetlearn/cpnet.py
cpnetlearn/dataset.py
cpnetlearn/ensemble.py
cpnetlearn/lptree.py
cpnetlearn/mdllearn.py
cpnetlearn/oracle.py
cpnetlearn/utils.py
cpnetlearn-0.1.0.dist-info/LICENSE
cpnetlearn-0.1.0.dist-info/METADATA
cpnetlearn-0.1.0.dist-info/WHEEL
cpnetlearn-0.1.0.dist-info/top_level.txt
cpnetlearn-0.1.0.dist-info/RECORD
