Metadata-Version: 2.1
Name: cpnetlearn
Version: 0.1.0
Summary: CP-net learning from positive examples
Author: Pierre-François Gimenez
License: MIT
License-File: LICENSE
Requires-Dist: numpy
Requires-Dist: scikit-learn
Requires-Dist: pandas
Requires-Dist: pomegranate
Requires-Dist: bnlearn
